{
  "indexes": [
    {
      "collectionGroup": "budgetLinks",
      "queryScope": "COLLECTION_GROUP",
      "fields": [
        { "fieldPath": "companyId", "order": "ASCENDING" },
        { "fieldPath": "budgetId", "order": "ASCENDING" }
      ]
    },
    {
      "collectionGroup": "budgetLinks",
      "queryScope": "COLLECTION_GROUP",
      "fields": [
        { "fieldPath": "budgetId", "order": "ASCENDING" },
        { "fieldPath": "companyId", "order": "ASCENDING" }
      ]
    },
    {
      "collectionGroup": "documentos",
      "queryScope": "COLLECTION",
      "fields": [
        { "fieldPath": "periodo", "order": "ASCENDING" },
        { "fieldPath": "status", "order": "ASCENDING" }
      ]
    }
  ],
  "fieldOverrides": []
}
